README.md
setup.cfg
setup.py
pbgpp/__init__.py
pbgpp.egg-info/PKG-INFO
pbgpp.egg-info/SOURCES.txt
pbgpp.egg-info/dependency_links.txt
pbgpp.egg-info/entry_points.txt
pbgpp.egg-info/not-zip-safe
pbgpp.egg-info/requires.txt
pbgpp.egg-info/top_level.txt
pbgpp/Application/CLI.py
pbgpp/Application/Handler.py
pbgpp/Application/__init__.py
pbgpp/BGP/Exceptions.py
pbgpp/BGP/Message.py
pbgpp/BGP/Packet.py
pbgpp/BGP/Statics.py
pbgpp/BGP/Translation.py
pbgpp/BGP/__init__.py
pbgpp/BGP/Keepalive/Message.py
pbgpp/BGP/Keepalive/__init__.py
pbgpp/BGP/Notification/Message.py
pbgpp/BGP/Notification/__init__.py
pbgpp/BGP/Open/Message.py
pbgpp/BGP/Open/OptionalParameter.py
pbgpp/BGP/Open/__init__.py
pbgpp/BGP/Open/Parameters/Authentication.py
pbgpp/BGP/Open/Parameters/Capability.py
pbgpp/BGP/Open/Parameters/Reserved.py
pbgpp/BGP/Open/Parameters/__init__.py
pbgpp/BGP/Open/Parameters/Capabilities/AddPath.py
pbgpp/BGP/Open/Parameters/Capabilities/BGPExtended.py
pbgpp/BGP/Open/Parameters/Capabilities/EnhancedRouteRefresh.py
pbgpp/BGP/Open/Parameters/Capabilities/ExtendedNextHopEncoding.py
pbgpp/BGP/Open/Parameters/Capabilities/FQDN.py
pbgpp/BGP/Open/Parameters/Capabilities/GracefulRestart.py
pbgpp/BGP/Open/Parameters/Capabilities/LongLivedGracefulRestart.py
pbgpp/BGP/Open/Parameters/Capabilities/MultipleRoutesToDestination.py
pbgpp/BGP/Open/Parameters/Capabilities/MultiprotocolExtensions.py
pbgpp/BGP/Open/Parameters/Capabilities/MultisessionBGP.py
pbgpp/BGP/Open/Parameters/Capabilities/OutboundRouteFiltering.py
pbgpp/BGP/Open/Parameters/Capabilities/RouteRefresh.py
pbgpp/BGP/Open/Parameters/Capabilities/SupportForDynamicCapability.py
pbgpp/BGP/Open/Parameters/Capabilities/SupportForFourOctetAS.py
pbgpp/BGP/Open/Parameters/Capabilities/Unknown.py
pbgpp/BGP/Open/Parameters/Capabilities/__init__.py
pbgpp/BGP/RouteRefresh/Message.py
pbgpp/BGP/RouteRefresh/__init__.py
pbgpp/BGP/Update/ASPathSegment.py
pbgpp/BGP/Update/Community.py
pbgpp/BGP/Update/ExtendedCommunity.py
pbgpp/BGP/Update/Flags.py
pbgpp/BGP/Update/LargeCommunity.py
pbgpp/BGP/Update/Message.py
pbgpp/BGP/Update/PathAttribute.py
pbgpp/BGP/Update/Route.py
pbgpp/BGP/Update/__init__.py
pbgpp/BGP/Update/PathAttributes/AIGP.py
